{
	"memberslist": [
		{
			"name": "Abiy Tefera and Mahder Tesfu",
			"memberid": "1001"
		},
		{
			"name": "Adane Mammo and Meron Girmma",
			"memberid": "1002"
		},
		{
			"name": "Alemayehu Roba and Yiftu Sira Abera",
			"memberid": "1003"
		},
		{
			"name": "Almaz Gebre Sillaassie",
			"memberid": "1004"
		},
		{
			"name": "Almaz Z. Yirgu",
			"memberid": "1005"
		},
		{
			"name": "Asaye Tsegga",
			"memberid": "1006"
		},
		{
			"name": "Ashenafi Deneke and Rahel Asrat",
			"memberid": "1007"
		},
		{
			"name": "Ayele Negash",
			"memberid": "1008"
		},
		{
			"name": "Aynalem Zeleke and Fitsum Hailemariam",
			"memberid": "1009"
		},
		{
			"name": "Azeb Kidane",
			"memberid": "1010"
		},
		{
			"name": "Banchiamlak Yimenu and Wayne kendrix",
			"memberid": "1011"
		},
		{
			"name": "Belay Gebre",
			"memberid": "1012"
		},
		{
			"name": "Birhanu Zelleke and Monique Michel",
			"memberid": "1013"
		},
		{
			"name": "Chris Heikavis Weaver",
			"memberid": "1014"
		},
		{
			"name": "Damena Bahiru",
			"memberid": "1015"
		},
		{
			"name": "Elias Dammena",
			"memberid": "1016"
		},
		{
			"name": "Etalemahu Demissie",
			"memberid": "1017"
		},
		{
			"name": "Ezra Mersha",
			"memberid": "1018"
		},
		{
			"name": "Fikre Basa and Frehiwot",
			"memberid": "1019"
		},
		{
			"name": "Fikrte Fisseha",
			"memberid": "1020"
		},
		{
			"name": "Getahun Assefa and Seble Tedla",
			"memberid": "1021"
		},
		{
			"name": "Getahun S. Woldie",
			"memberid": "1022"
		},
		{
			"name": "Girum Tadesse and Frehiwot Mengesha",
			"memberid": "1023"
		},
		{
			"name": "Habtamu Zewde and Fantanesh Sahalu",
			"memberid": "1024"
		},
		{
			"name": "Kassahun Tamarat",
			"memberid": "1025"
		},
		{
			"name": "Mahlet Gelagay and Anteneh Getachew",
			"memberid": "1026"
		},
		{
			"name": "Mateweos Yeberta Hailmariam",
			"memberid": "1027"
		},
		{
			"name": "Mehiret Gebru Berehe",
			"memberid": "1028"
		},
		{
			"name": "Mekbib Degaga and Hable Mammo",
			"memberid": "1029"
		},
		{
			"name": "Negash Hagos and Adgalidgn Woldemichael",
			"memberid": "1030"
		},
		{
			"name": "Nunu Y. Belete and Sileshi Dereje",
			"memberid": "1031"
		},
		{
			"name": "Solomon Bayou",
			"memberid": "1032"
		},
		{
			"name": "Solomon Mammo",
			"memberid": "1033"
		},
		{
			"name": "Solomon Tefera and Eden Abraham",
			"memberid": "1034"
		},
		{
			"name": "Tadelech Demissie",
			"memberid": "1035"
		},
		{
			"name": "Tesfu Tadesse",
			"memberid": "1036"
		},
		{
			"name": "Tewodros Ayano and Tihut Wolde",
			"memberid": "1037"
		},
		{
			"name": "Tibebu Gelaw",
			"memberid": "1038"
		},
		{
			"name": "Tigist Demissie",
			"memberid": "1039"
		},
		{
			"name": "Tigist Rambert",
			"memberid": "1040"
		},
		{
			"name": "Tirsit Ceta Benvegnu",
			"memberid": "1041"
		},
		{
			"name": "Tirsit Kibkabe",
			"memberid": "1042"
		},
		{
			"name": "Yared Bekele and Misrak",
			"memberid": "1043"
		},
		{
			"name": "Yared Kebede",
			"memberid": "1044"
		},
		{
			"name": "Yeabsira Eshetu",
			"memberid": "1045"
		},
		{
			"name": "Yemane Reta",
			"memberid": "1046"
		},
		{
			"name": "Yerom Yesuf",
			"memberid": "1047"
		},
		{
			"name": "Yeshialem W. Mengistu",
			"memberid": "1048"
		},
		{
			"name": "Yeheyies Tekleselassie and Mekdes",
			"memberid": "1049"
		},
		{
			"name": "Yimenu Getinet",
			"memberid": "1050"
		},
		{
			"name": "Yonas Endaweq and Meskerem Abera",
			"memberid": "1051"
		},
		{
			"name": "Abaynesh Demissie",
			"memberid": "1052"
		},
		{
			"name": "Sophia",
			"memberid": "1053"
		},
		{
			"name": "Biniam and Helen",
			"memberid": "1055"
		},
		{
			"name": "Samuel Varush",
			"memberid": "1056"
		},
		{
			"name": "etu and assegid",
			"memberid": "1057"
		}
	]
}
